timber/__init__.py
timber/compat.py
timber/flusher.py
timber/formatter.py
timber/frame.py
timber/handler.py
timber/helpers.py
timber/log_entry.py
timber/uploader.py
timber-2.1.0.dist-info/LICENSE.md
timber-2.1.0.dist-info/METADATA
timber-2.1.0.dist-info/WHEEL
timber-2.1.0.dist-info/top_level.txt
timber-2.1.0.dist-info/RECORD
