Metadata-Version: 2.1
Name: timber
Version: 2.1.0
Summary: timber.io client API library
Home-page: https://github.com/timberio/timber-python
Author: Timber Technologies, Inc.
Author-email: help@timber.io
License: MIT
Download-URL: https://github.com/timberio/timber-python/tarball/2.1.0
Keywords: api,timber,logging,client
Platform: UNKNOWN
Classifier: Intended Audience :: Developers
Classifier: License :: OSI Approved :: MIT License
Classifier: Operating System :: OS Independent
Classifier: Programming Language :: Python :: 2
Classifier: Programming Language :: Python :: 2.7
Classifier: Programming Language :: Python :: 3
Classifier: Programming Language :: Python :: 3.4
Classifier: Programming Language :: Python :: 3.5
Classifier: Programming Language :: Python :: 3.6
Classifier: Programming Language :: Python
Classifier: Topic :: Software Development :: Libraries :: Python Modules
Requires-Dist: requests (>=2.18.4)
Requires-Dist: msgpack (>=0.5.6)
